notate/__init__.py
notate/__main__.py
notate/code_parser.py
notate/default_fields_generator.py
notate/document_parser.py
notate/dotfile_manager.py
notate/email_parser.py
notate/meeting_parser.py
notate/note.py
notate/take_note.py
notate/utils.py
notate/video_parser.py
notate/web_parser.py
notate-0.1.0.dist-info/entry_points.txt
notate-0.1.0.dist-info/LICENSE
notate-0.1.0.dist-info/WHEEL
notate-0.1.0.dist-info/METADATA
notate-0.1.0.dist-info/RECORD
