Metadata-Version: 2.1
Name: notate
Version: 0.1.0
Summary: Note generation scripts for note-taking with Notable.
License: MIT
Keywords: notable
Author: David Cabinian
Author-email: dhcabinian@gmail.com
Requires-Python: >=3.7,<4.0
Classifier: License :: OSI Approved :: MIT License
Classifier: Programming Language :: Python :: 3
Classifier: Programming Language :: Python :: 3.7
Classifier: Programming Language :: Python :: 3.8
Requires-Dist: PyInquirer (>=1.0.3,<2.0.0)
Requires-Dist: icalendar (>=4.0.4,<5.0.0)
Requires-Dist: pdfkit (>=0.6.1,<0.7.0)
Requires-Dist: pendulum (>=2.0.5,<3.0.0)
Requires-Dist: requests (>=2.23.0,<3.0.0)
Requires-Dist: youtube_dl (>=2020.2.16,<2021.0.0)
